test/__init__.py
test/convolution/__init__.py
test/convolution/test_base2D.py
test/convolution/test_base3D.py
test/convolution/test_convEncoder.py
test/convolution/test_conv_base2D.py
test/convolution/test_conv_base3D.py
test/convolution/test_convolution2D.py
test/convolution/test_convolution3D.py
test/convolution/test_seq_base2D.py
test/masking/__init__.py
test/masking/test_mask2D.py
test/masking/test_mask3D.py
test/pooling/__init__.py
test/pooling/test_mask_avg2D_pooling.py
test/pooling/test_mask_avg3D_pooling.py
test/pooling/test_mask_max2D_pooling.py
test/pooling/test_mask_max3D_pooling.py
test/recurrent/__init__.py
test/recurrent/test_bidirectional_rnn_encoder.py
test/recurrent/test_lstm_peephole.py
test/recurrent/test_rnn_base.py
test/recurrent/test_rnn_cell.py
test/recurrent/test_rnn_decoder.py
test/recurrent/test_rnn_decoder_with_decoding_size.py
test/recurrent/test_rnn_encoder.py
test/util/__init__.py
test/util/test_flatten.py
test/util/test_padding_layer.py
test/util/test_pick.py
test/wrapper/__init__.py
test/wrapper/test_mask_to_seq.py
yklz/__init__.py
yklz/backend/__init__.py
yklz/backend/tensorflow_backend.py
yklz/convolution/__init__.py
yklz/convolution/convEncoder.py
yklz/convolution/mask_ConvNet.py
yklz/masking/__init__.py
yklz/masking/maskConv.py
yklz/pooling/__init__.py
yklz/pooling/mask_pooling.py
yklz/recurrent/__init__.py
yklz/recurrent/bidirectional_rnn_encoder.py
yklz/recurrent/lstm_peephole.py
yklz/recurrent/rnn_cell.py
yklz/recurrent/rnn_decoder.py
yklz/recurrent/rnn_encoder.py
yklz/util/__init__.py
yklz/util/flatten.py
yklz/util/padding_layer.py
yklz/util/pick.py
yklz/wrapper/__init__.py
yklz/wrapper/mask_to_seq.py
yoctol_keras_layer_zoo-0.7.0.dist-info/DESCRIPTION.rst
yoctol_keras_layer_zoo-0.7.0.dist-info/METADATA
yoctol_keras_layer_zoo-0.7.0.dist-info/RECORD
yoctol_keras_layer_zoo-0.7.0.dist-info/WHEEL
yoctol_keras_layer_zoo-0.7.0.dist-info/metadata.json
yoctol_keras_layer_zoo-0.7.0.dist-info/top_level.txt
